{
  "nodes": [
    {
      "BACnetID": "85e67c6ff061ed0c",
      "id": 0,
      "name": "aline",
      "gender": null,
      "birthday": null,
      "country": null,
      "town": null,
      "language": null,
      "status": null,
      "hopLayer": 3
    },
    {
      "BACnetID": "7d1411a1aa9042a0",
      "id": 1,
      "name": "ben",
      "gender": null,
      "birthday": null,
      "country": null,
      "town": null,
      "language": null,
      "status": null,
      "hopLayer": 3
    },
    {
      "BACnetID": "75f4560ba57f4b79",
      "id": 2,
      "name": "caroline",
      "gender": null,
      "birthday": null,
      "country": null,
      "town": null,
      "language": null,
      "status": null,
      "hopLayer": 10000
    },
    {
      "BACnetID": "afef535c7fc8c4a9",
      "id": 3,
      "name": "david",
      "gender": null,
      "birthday": null,
      "country": null,
      "town": null,
      "language": null,
      "status": null,
      "hopLayer": 2
    },
    {
      "BACnetID": "671c84d65ecd4bb6",
      "id": 4,
      "name": "esther",
      "gender": null,
      "birthday": null,
      "country": null,
      "town": null,
      "language": null,
      "status": null,
      "hopLayer": 1
    },
    {
      "BACnetID": "7f288945343227f4",
      "id": 5,
      "name": "eveline",
      "gender": null,
      "birthday": null,
      "country": null,
      "town": null,
      "language": null,
      "status": null,
      "hopLayer": 10000
    },
    {
      "BACnetID": "b7c1732f751a58ff",
      "id": 6,
      "name": "fitzgerald",
      "gender": null,
      "birthday": null,
      "country": null,
      "town": null,
      "language": null,
      "status": null,
      "hopLayer": 10000
    },
    {
      "BACnetID": "fc9ae599e33046b5",
      "id": 7,
      "name": "georgia",
      "gender": null,
      "birthday": null,
      "country": null,
      "town": null,
      "language": null,
      "status": null,
      "hopLayer": 4
    },
    {
      "BACnetID": "4894ca5029f230a0",
      "id": 8,
      "name": "henry",
      "gender": null,
      "birthday": null,
      "country": null,
      "town": null,
      "language": null,
      "status": null,
      "hopLayer": 4
    },
    {
      "BACnetID": "31efbf5bb7a55cb0",
      "id": 9,
      "name": "isabelle",
      "gender": null,
      "birthday": null,
      "country": null,
      "town": null,
      "language": null,
      "status": null,
      "hopLayer": 10000
    },
    {
      "BACnetID": "989910ef23b57bb6",
      "id": 10,
      "name": "julius",
      "gender": null,
      "birthday": null,
      "country": null,
      "town": null,
      "language": null,
      "status": null,
      "hopLayer": 2
    },
    {
      "BACnetID": "dfceab3e63b9defe",
      "id": 11,
      "name": "pascal",
      "gender": null,
      "birthday": null,
      "country": null,
      "town": null,
      "language": null,
      "status": null,
      "hopLayer": 1
    },
    {
      "BACnetID": "c598f981d48a232d",
      "id": 12,
      "name": "phillip",
      "gender": null,
      "birthday": null,
      "country": null,
      "town": null,
      "language": null,
      "status": null,
      "hopLayer": 1
    },
    {
      "BACnetID": "3b6454f890d6a8bd",
      "id": 13,
      "name": "sebastian",
      "gender": null,
      "birthday": null,
      "country": null,
      "town": null,
      "language": null,
      "status": null,
      "hopLayer": 1
    },
    {
      "BACnetID": "6970e21c691dee7f",
      "id": 14,
      "name": "vera",
      "gender": null,
      "birthday": null,
      "country": null,
      "town": null,
      "language": null,
      "status": null,
      "hopLayer": 0
    },
    {
      "BACnetID": "7e8f4d9fc590d387",
      "id": 15,
      "name": "veri",
      "gender": null,
      "birthday": null,
      "country": null,
      "town": null,
      "language": null,
      "status": null,
      "hopLayer": 10000
    },
    {
      "BACnetID": "a245c02edfeaab37",
      "id": 16,
      "name": "yasmin",
      "gender": null,
      "birthday": null,
      "country": null,
      "town": null,
      "language": null,
      "status": null,
      "hopLayer": 1
    }
  ],
  "links": [
    {
      "source": 0,
      "target": 16
    },
    {
      "source": 0,
      "target": 7
    },
    {
      "source": 0,
      "target": 8
    },
    {
      "source": 1,
      "target": 0
    },
    {
      "source": 1,
      "target": 14
    },
    {
      "source": 1,
      "target": 4
    },
    {
      "source": 1,
      "target": 16
    },
    {
      "source": 4,
      "target": 16
    },
    {
      "source": 4,
      "target": 14
    },
    {
      "source": 4,
      "target": 3
    },
    {
      "source": 10,
      "target": 0
    },
    {
      "source": 10,
      "target": 1
    },
    {
      "source": 11,
      "target": 13
    },
    {
      "source": 11,
      "target": 12
    },
    {
      "source": 12,
      "target": 13
    },
    {
      "source": 12,
      "target": 11
    },
    {
      "source": 13,
      "target": 12
    },
    {
      "source": 13,
      "target": 11
    },
    {
      "source": 14,
      "target": 4
    },
    {
      "source": 14,
      "target": 16
    },
    {
      "source": 14,
      "target": 13
    },
    {
      "source": 14,
      "target": 11
    },
    {
      "source": 14,
      "target": 12
    },
    {
      "source": 16,
      "target": 14
    },
    {
      "source": 16,
      "target": 4
    },
    {
      "source": 16,
      "target": 10
    }
  ]
}